{"stats":{"minecraft:crafted":{"minecraft:oak_boat":1,"minecraft:oak_planks":8,"minecraft:stick":4,"minecraft:wooden_pickaxe":1,"minecraft:stone_pickaxe":1,"minecraft:stone_axe":1},"minecraft:used":{"minecraft:bread":3,"minecraft:stone_pickaxe":37,"minecraft:wooden_pickaxe":3,"minecraft:stone_axe":123,"minecraft:torch":1,"minecraft:oak_boat":1},"minecraft:killed":{"minecraft:sheep":3,"adventurez:deer":1,"minecraft:pig":1},"minecraft:dropped":{"biomesoplenty:redwood_sapling":3,"biomesoplenty:redwood_wood":2,"minecraft:wooden_pickaxe":1,"natures_spirit:sugi_sapling":33},"minecraft:picked_up":{"minecraft:birch_log":25,"biomesoplenty:redwood_log":16,"natures_spirit:sugi_sapling":33,"minecraft:stick":23,"minecraft:crafting_table":1,"minecraft:pumpkin":3,"natures_spirit:sugi_log":97,"minecraft:porkchop":2,"minecraft:oak_log":17,"adventurez:raw_venison":3,"minecraft:oak_boat":1,"biomesoplenty:redwood_sapling":3,"minecraft:bamboo":14,"biomesoplenty:redwood_wood":5,"minecraft:mutton":7,"minecraft:birch_sapling":4,"minecraft:coal":24,"minecraft:white_wool":4,"minecraft:cobblestone":12,"minecraft:magma_block":1},"minecraft:mined":{"minecraft:seagrass":1,"minecraft:magma_block":1,"minecraft:birch_log":25,"natures_spirit:sugi_log":51,"minecraft:pumpkin":3,"minecraft:oak_log":17,"natures_spirit:sugi_leaves":1,"minecraft:coal_ore":24,"biomesoplenty:redwood_log":16,"minecraft:bamboo":3,"minecraft:stone":12,"biomesoplenty:redwood_wood":3},"minecraft:custom":{"minecraft:time_since_rest":30031,"minecraft:sprint_one_cm":55748,"minecraft:damage_taken":90,"minecraft:walk_one_cm":63700,"minecraft:mob_kills":5,"minecraft:drop":5,"minecraft:damage_dealt":479,"minecraft:swim_one_cm":25164,"minecraft:interact_with_crafting_table":6,"minecraft:fly_one_cm":51418,"minecraft:open_chest":4,"minecraft:crouch_one_cm":121,"minecraft:play_time":30031,"minecraft:sneak_time":683,"minecraft:walk_under_water_one_cm":20420,"minecraft:boat_one_cm":25018,"minecraft:jump":269,"minecraft:walk_on_water_one_cm":5963,"minecraft:time_since_death":30031,"minecraft:total_world_time":30031,"minecraft:climb_one_cm":214,"minecraft:fall_one_cm":8227}},"DataVersion":3955}